{"nodes": [{"id": "e_knowledge_obsidianvault_gitnexus_gitnexus_test_fixtures_lang_resolution_swift_await_try_app_swift", "label": "App.swift", "file_type": "code", "source_file": "E:\\_Knowledge\\ObsidianVault\\GitNexus\\gitnexus\\test\\fixtures\\lang-resolution\\swift-await-try\\App.swift", "source_location": "L1"}, {"id": "app_processawait", "label": "processAwait()", "file_type": "code", "source_file": "E:\\_Knowledge\\ObsidianVault\\GitNexus\\gitnexus\\test\\fixtures\\lang-resolution\\swift-await-try\\App.swift", "source_location": "L1"}, {"id": "app_processtry", "label": "processTry()", "file_type": "code", "source_file": "E:\\_Knowledge\\ObsidianVault\\GitNexus\\gitnexus\\test\\fixtures\\lang-resolution\\swift-await-try\\App.swift", "source_location": "L6"}], "edges": [{"source": "e_knowledge_obsidianvault_gitnexus_gitnexus_test_fixtures_lang_resolution_swift_await_try_app_swift", "target": "app_processawait", "relation": "contains", "confidence": "EXTRACTED", "source_file": "E:\\_Knowledge\\ObsidianVault\\GitNexus\\gitnexus\\test\\fixtures\\lang-resolution\\swift-await-try\\App.swift", "source_location": "L1", "weight": 1.0}, {"source": "e_knowledge_obsidianvault_gitnexus_gitnexus_test_fixtures_lang_resolution_swift_await_try_app_swift", "target": "app_processtry", "relation": "contains", "confidence": "EXTRACTED", "source_file": "E:\\_Knowledge\\ObsidianVault\\GitNexus\\gitnexus\\test\\fixtures\\lang-resolution\\swift-await-try\\App.swift", "source_location": "L6", "weight": 1.0}], "raw_calls": [{"caller_nid": "app_processawait", "callee": "fetchUser", "source_file": "E:\\_Knowledge\\ObsidianVault\\GitNexus\\gitnexus\\test\\fixtures\\lang-resolution\\swift-await-try\\App.swift", "source_location": "L2"}, {"caller_nid": "app_processawait", "callee": "save", "source_file": "E:\\_Knowledge\\ObsidianVault\\GitNexus\\gitnexus\\test\\fixtures\\lang-resolution\\swift-await-try\\App.swift", "source_location": "L3"}, {"caller_nid": "app_processtry", "callee": "parseRepo", "source_file": "E:\\_Knowledge\\ObsidianVault\\GitNexus\\gitnexus\\test\\fixtures\\lang-resolution\\swift-await-try\\App.swift", "source_location": "L7"}, {"caller_nid": "app_processtry", "callee": "save", "source_file": "E:\\_Knowledge\\ObsidianVault\\GitNexus\\gitnexus\\test\\fixtures\\lang-resolution\\swift-await-try\\App.swift", "source_location": "L8"}]}