{"nodes": [{"id": "index", "label": "index.ts", "file_type": "code", "source_file": "tolaria/src/mock-tauri/index.ts", "source_location": "L1"}, {"id": "index_istauri", "label": "isTauri()", "file_type": "code", "source_file": "tolaria/src/mock-tauri/index.ts", "source_location": "L13"}, {"id": "index_resolvemockhandler", "label": "resolveMockHandler()", "file_type": "code", "source_file": "tolaria/src/mock-tauri/index.ts", "source_location": "L27"}, {"id": "index_mockinvoke", "label": "mockInvoke()", "file_type": "code", "source_file": "tolaria/src/mock-tauri/index.ts", "source_location": "L34"}], "edges": [{"source": "index", "target": "mock_content", "relation": "imports_from", "confidence": "EXTRACTED", "source_file": "tolaria/src/mock-tauri/index.ts", "source_location": "L7", "weight": 1.0}, {"source": "index", "target": "mock_handlers", "relation": "imports_from", "confidence": "EXTRACTED", "source_file": "tolaria/src/mock-tauri/index.ts", "source_location": "L8", "weight": 1.0}, {"source": "index", "target": "vault_api", "relation": "imports_from", "confidence": "EXTRACTED", "source_file": "tolaria/src/mock-tauri/index.ts", "source_location": "L9", "weight": 1.0}, {"source": "index", "target": "index_istauri", "relation": "contains", "confidence": "EXTRACTED", "source_file": "tolaria/src/mock-tauri/index.ts", "source_location": "L13", "weight": 1.0}, {"source": "index", "target": "index_resolvemockhandler", "relation": "contains", "confidence": "EXTRACTED", "source_file": "tolaria/src/mock-tauri/index.ts", "source_location": "L27", "weight": 1.0}, {"source": "index", "target": "index_mockinvoke", "relation": "contains", "confidence": "EXTRACTED", "source_file": "tolaria/src/mock-tauri/index.ts", "source_location": "L34", "weight": 1.0}, {"source": "index_mockinvoke", "target": "index_resolvemockhandler", "relation": "calls", "confidence": "EXTRACTED", "source_file": "tolaria/src/mock-tauri/index.ts", "source_location": "L38", "weight": 1.0}]}