{"nodes": [{"id": "usediffmode", "label": "useDiffMode.ts", "file_type": "code", "source_file": "tolaria/src/hooks/useDiffMode.ts", "source_location": "L1"}, {"id": "usediffmode_loaddiffforpath", "label": "loadDiffForPath()", "file_type": "code", "source_file": "tolaria/src/hooks/useDiffMode.ts", "source_location": "L30"}, {"id": "usediffmode_loadcommitdiffforpath", "label": "loadCommitDiffForPath()", "file_type": "code", "source_file": "tolaria/src/hooks/useDiffMode.ts", "source_location": "L49"}, {"id": "usediffmode_shouldhandlependingcommitdiffrequest", "label": "shouldHandlePendingCommitDiffRequest()", "file_type": "code", "source_file": "tolaria/src/hooks/useDiffMode.ts", "source_location": "L69"}, {"id": "usediffmode_hascommithash", "label": "hasCommitHash()", "file_type": "code", "source_file": "tolaria/src/hooks/useDiffMode.ts", "source_location": "L76"}, {"id": "usediffmode_buildguardeddiffstatesetters", "label": "buildGuardedDiffStateSetters()", "file_type": "code", "source_file": "tolaria/src/hooks/useDiffMode.ts", "source_location": "L80"}, {"id": "usediffmode_runpendingcommitdiffrequest", "label": "runPendingCommitDiffRequest()", "file_type": "code", "source_file": "tolaria/src/hooks/useDiffMode.ts", "source_location": "L92"}, {"id": "usediffmode_usependingcommitdiffrequest", "label": "usePendingCommitDiffRequest()", "file_type": "code", "source_file": "tolaria/src/hooks/useDiffMode.ts", "source_location": "L124"}, {"id": "usediffmode_usediffmode", "label": "useDiffMode()", "file_type": "code", "source_file": "tolaria/src/hooks/useDiffMode.ts", "source_location": "L156"}], "edges": [{"source": "usediffmode", "target": "react", "relation": "imports_from", "confidence": "EXTRACTED", "source_file": "tolaria/src/hooks/useDiffMode.ts", "source_location": "L1", "weight": 1.0}, {"source": "usediffmode", "target": "usediffmode_loaddiffforpath", "relation": "contains", "confidence": "EXTRACTED", "source_file": "tolaria/src/hooks/useDiffMode.ts", "source_location": "L30", "weight": 1.0}, {"source": "usediffmode", "target": "usediffmode_loadcommitdiffforpath", "relation": "contains", "confidence": "EXTRACTED", "source_file": "tolaria/src/hooks/useDiffMode.ts", "source_location": "L49", "weight": 1.0}, {"source": "usediffmode", "target": "usediffmode_shouldhandlependingcommitdiffrequest", "relation": "contains", "confidence": "EXTRACTED", "source_file": "tolaria/src/hooks/useDiffMode.ts", "source_location": "L69", "weight": 1.0}, {"source": "usediffmode", "target": "usediffmode_hascommithash", "relation": "contains", "confidence": "EXTRACTED", "source_file": "tolaria/src/hooks/useDiffMode.ts", "source_location": "L76", "weight": 1.0}, {"source": "usediffmode", "target": "usediffmode_buildguardeddiffstatesetters", "relation": "contains", "confidence": "EXTRACTED", "source_file": "tolaria/src/hooks/useDiffMode.ts", "source_location": "L80", "weight": 1.0}, {"source": "usediffmode", "target": "usediffmode_runpendingcommitdiffrequest", "relation": "contains", "confidence": "EXTRACTED", "source_file": "tolaria/src/hooks/useDiffMode.ts", "source_location": "L92", "weight": 1.0}, {"source": "usediffmode", "target": "usediffmode_usependingcommitdiffrequest", "relation": "contains", "confidence": "EXTRACTED", "source_file": "tolaria/src/hooks/useDiffMode.ts", "source_location": "L124", "weight": 1.0}, {"source": "usediffmode", "target": "usediffmode_usediffmode", "relation": "contains", "confidence": "EXTRACTED", "source_file": "tolaria/src/hooks/useDiffMode.ts", "source_location": "L156", "weight": 1.0}, {"source": "usediffmode_runpendingcommitdiffrequest", "target": "usediffmode_hascommithash", "relation": "calls", "confidence": "EXTRACTED", "source_file": "tolaria/src/hooks/useDiffMode.ts", "source_location": "L101", "weight": 1.0}, {"source": "usediffmode_runpendingcommitdiffrequest", "target": "usediffmode_loadcommitdiffforpath", "relation": "calls", "confidence": "EXTRACTED", "source_file": "tolaria/src/hooks/useDiffMode.ts", "source_location": "L102", "weight": 1.0}, {"source": "usediffmode_runpendingcommitdiffrequest", "target": "usediffmode_buildguardeddiffstatesetters", "relation": "calls", "confidence": "EXTRACTED", "source_file": "tolaria/src/hooks/useDiffMode.ts", "source_location": "L106", "weight": 1.0}, {"source": "usediffmode_runpendingcommitdiffrequest", "target": "usediffmode_loaddiffforpath", "relation": "calls", "confidence": "EXTRACTED", "source_file": "tolaria/src/hooks/useDiffMode.ts", "source_location": "L108", "weight": 1.0}, {"source": "usediffmode_usediffmode", "target": "usediffmode_usependingcommitdiffrequest", "relation": "calls", "confidence": "EXTRACTED", "source_file": "tolaria/src/hooks/useDiffMode.ts", "source_location": "L168", "weight": 1.0}]}