{"nodes": [{"id": "types", "label": "types.ts", "file_type": "code", "source_file": "GitNexus/gitnexus/src/core/embeddings/types.ts", "source_location": "L1"}, {"id": "types_isembeddablelabel", "label": "isEmbeddableLabel()", "file_type": "code", "source_file": "GitNexus/gitnexus/src/core/embeddings/types.ts", "source_location": "L89"}, {"id": "types_ischunkablelabel", "label": "isChunkableLabel()", "file_type": "code", "source_file": "GitNexus/gitnexus/src/core/embeddings/types.ts", "source_location": "L95"}, {"id": "types_isshortlabel", "label": "isShortLabel()", "file_type": "code", "source_file": "GitNexus/gitnexus/src/core/embeddings/types.ts", "source_location": "L101"}, {"id": "types_dedupbestchunks", "label": "dedupBestChunks()", "file_type": "code", "source_file": "GitNexus/gitnexus/src/core/embeddings/types.ts", "source_location": "L324"}, {"id": "types_collectbestchunks", "label": "collectBestChunks()", "file_type": "code", "source_file": "GitNexus/gitnexus/src/core/embeddings/types.ts", "source_location": "L352"}], "edges": [{"source": "types", "target": "types_isembeddablelabel", "relation": "contains", "confidence": "EXTRACTED", "source_file": "GitNexus/gitnexus/src/core/embeddings/types.ts", "source_location": "L89", "weight": 1.0}, {"source": "types", "target": "types_ischunkablelabel", "relation": "contains", "confidence": "EXTRACTED", "source_file": "GitNexus/gitnexus/src/core/embeddings/types.ts", "source_location": "L95", "weight": 1.0}, {"source": "types", "target": "types_isshortlabel", "relation": "contains", "confidence": "EXTRACTED", "source_file": "GitNexus/gitnexus/src/core/embeddings/types.ts", "source_location": "L101", "weight": 1.0}, {"source": "types", "target": "types_dedupbestchunks", "relation": "contains", "confidence": "EXTRACTED", "source_file": "GitNexus/gitnexus/src/core/embeddings/types.ts", "source_location": "L324", "weight": 1.0}, {"source": "types", "target": "types_collectbestchunks", "relation": "contains", "confidence": "EXTRACTED", "source_file": "GitNexus/gitnexus/src/core/embeddings/types.ts", "source_location": "L352", "weight": 1.0}, {"source": "types_collectbestchunks", "target": "types_dedupbestchunks", "relation": "calls", "confidence": "EXTRACTED", "source_file": "GitNexus/gitnexus/src/core/embeddings/types.ts", "source_location": "L364", "weight": 1.0}]}