{"nodes": [{"id": "note_drop_wikilink_spec", "label": "note-drop-wikilink.spec.ts", "file_type": "code", "source_file": "tolaria/tests/smoke/note-drop-wikilink.spec.ts", "source_location": "L1"}, {"id": "note_drop_wikilink_spec_opennote", "label": "openNote()", "file_type": "code", "source_file": "tolaria/tests/smoke/note-drop-wikilink.spec.ts", "source_location": "L16"}], "edges": [{"source": "note_drop_wikilink_spec", "target": "test", "relation": "imports_from", "confidence": "EXTRACTED", "source_file": "tolaria/tests/smoke/note-drop-wikilink.spec.ts", "source_location": "L1", "weight": 1.0}, {"source": "note_drop_wikilink_spec", "target": "path", "relation": "imports_from", "confidence": "EXTRACTED", "source_file": "tolaria/tests/smoke/note-drop-wikilink.spec.ts", "source_location": "L2", "weight": 1.0}, {"source": "note_drop_wikilink_spec", "target": "fixturevault", "relation": "imports_from", "confidence": "EXTRACTED", "source_file": "tolaria/tests/smoke/note-drop-wikilink.spec.ts", "source_location": "L3", "weight": 1.0}, {"source": "note_drop_wikilink_spec", "target": "note_drop_wikilink_spec_opennote", "relation": "contains", "confidence": "EXTRACTED", "source_file": "tolaria/tests/smoke/note-drop-wikilink.spec.ts", "source_location": "L16", "weight": 1.0}]}