{"nodes": [{"id": "e_knowledge_obsidianvault_gitnexus_gitnexus_src_core_ingestion_import_resolvers_rust_ts", "label": "rust.ts", "file_type": "code", "source_file": "E:\\_Knowledge\\ObsidianVault\\GitNexus\\gitnexus\\src\\core\\ingestion\\import-resolvers\\rust.ts", "source_location": "L1"}, {"id": "rust_resolverustimportinternal", "label": "resolveRustImportInternal()", "file_type": "code", "source_file": "E:\\_Knowledge\\ObsidianVault\\GitNexus\\gitnexus\\src\\core\\ingestion\\import-resolvers\\rust.ts", "source_location": "L12"}, {"id": "rust_tryrustmodulepath", "label": "tryRustModulePath()", "file_type": "code", "source_file": "E:\\_Knowledge\\ObsidianVault\\GitNexus\\gitnexus\\src\\core\\ingestion\\import-resolvers\\rust.ts", "source_location": "L66"}], "edges": [{"source": "e_knowledge_obsidianvault_gitnexus_gitnexus_src_core_ingestion_import_resolvers_rust_ts", "target": "rust_resolverustimportinternal", "relation": "contains", "confidence": "EXTRACTED", "source_file": "E:\\_Knowledge\\ObsidianVault\\GitNexus\\gitnexus\\src\\core\\ingestion\\import-resolvers\\rust.ts", "source_location": "L12", "weight": 1.0}, {"source": "e_knowledge_obsidianvault_gitnexus_gitnexus_src_core_ingestion_import_resolvers_rust_ts", "target": "rust_tryrustmodulepath", "relation": "contains", "confidence": "EXTRACTED", "source_file": "E:\\_Knowledge\\ObsidianVault\\GitNexus\\gitnexus\\src\\core\\ingestion\\import-resolvers\\rust.ts", "source_location": "L66", "weight": 1.0}, {"source": "rust_resolverustimportinternal", "target": "rust_tryrustmodulepath", "relation": "calls", "confidence": "EXTRACTED", "source_file": "E:\\_Knowledge\\ObsidianVault\\GitNexus\\gitnexus\\src\\core\\ingestion\\import-resolvers\\rust.ts", "source_location": "L24", "weight": 1.0}], "raw_calls": [{"caller_nid": "rust_resolverustimportinternal", "callee": "startsWith", "source_file": "E:\\_Knowledge\\ObsidianVault\\GitNexus\\gitnexus\\src\\core\\ingestion\\import-resolvers\\rust.ts", "source_location": "L19"}, {"caller_nid": "rust_resolverustimportinternal", "callee": "replace", "source_file": "E:\\_Knowledge\\ObsidianVault\\GitNexus\\gitnexus\\src\\core\\ingestion\\import-resolvers\\rust.ts", "source_location": "L21"}, {"caller_nid": "rust_resolverustimportinternal", "callee": "slice", "source_file": "E:\\_Knowledge\\ObsidianVault\\GitNexus\\gitnexus\\src\\core\\ingestion\\import-resolvers\\rust.ts", "source_location": "L21"}, {"caller_nid": "rust_resolverustimportinternal", "callee": "startsWith", "source_file": "E:\\_Knowledge\\ObsidianVault\\GitNexus\\gitnexus\\src\\core\\ingestion\\import-resolvers\\rust.ts", "source_location": "L34"}, {"caller_nid": "rust_resolverustimportinternal", "callee": "slice", "source_file": "E:\\_Knowledge\\ObsidianVault\\GitNexus\\gitnexus\\src\\core\\ingestion\\import-resolvers\\rust.ts", "source_location": "L36"}, {"caller_nid": "rust_resolverustimportinternal", "callee": "split", "source_file": "E:\\_Knowledge\\ObsidianVault\\GitNexus\\gitnexus\\src\\core\\ingestion\\import-resolvers\\rust.ts", "source_location": "L36"}, {"caller_nid": "rust_resolverustimportinternal", "callee": "pop", "source_file": "E:\\_Knowledge\\ObsidianVault\\GitNexus\\gitnexus\\src\\core\\ingestion\\import-resolvers\\rust.ts", "source_location": "L37"}, {"caller_nid": "rust_resolverustimportinternal", "callee": "replace", "source_file": "E:\\_Knowledge\\ObsidianVault\\GitNexus\\gitnexus\\src\\core\\ingestion\\import-resolvers\\rust.ts", "source_location": "L38"}, {"caller_nid": "rust_resolverustimportinternal", "callee": "slice", "source_file": "E:\\_Knowledge\\ObsidianVault\\GitNexus\\gitnexus\\src\\core\\ingestion\\import-resolvers\\rust.ts", "source_location": "L38"}, {"caller_nid": "rust_resolverustimportinternal", "callee": "join", "source_file": "E:\\_Knowledge\\ObsidianVault\\GitNexus\\gitnexus\\src\\core\\ingestion\\import-resolvers\\rust.ts", "source_location": "L39"}, {"caller_nid": "rust_resolverustimportinternal", "callee": "startsWith", "source_file": "E:\\_Knowledge\\ObsidianVault\\GitNexus\\gitnexus\\src\\core\\ingestion\\import-resolvers\\rust.ts", "source_location": "L43"}, {"caller_nid": "rust_resolverustimportinternal", "callee": "slice", "source_file": "E:\\_Knowledge\\ObsidianVault\\GitNexus\\gitnexus\\src\\core\\ingestion\\import-resolvers\\rust.ts", "source_location": "L45"}, {"caller_nid": "rust_resolverustimportinternal", "callee": "split", "source_file": "E:\\_Knowledge\\ObsidianVault\\GitNexus\\gitnexus\\src\\core\\ingestion\\import-resolvers\\rust.ts", "source_location": "L45"}, {"caller_nid": "rust_resolverustimportinternal", "callee": "replace", "source_file": "E:\\_Knowledge\\ObsidianVault\\GitNexus\\gitnexus\\src\\core\\ingestion\\import-resolvers\\rust.ts", "source_location": "L46"}, {"caller_nid": "rust_resolverustimportinternal", "callee": "slice", "source_file": "E:\\_Knowledge\\ObsidianVault\\GitNexus\\gitnexus\\src\\core\\ingestion\\import-resolvers\\rust.ts", "source_location": "L46"}, {"caller_nid": "rust_resolverustimportinternal", "callee": "join", "source_file": "E:\\_Knowledge\\ObsidianVault\\GitNexus\\gitnexus\\src\\core\\ingestion\\import-resolvers\\rust.ts", "source_location": "L47"}, {"caller_nid": "rust_resolverustimportinternal", "callee": "includes", "source_file": "E:\\_Knowledge\\ObsidianVault\\GitNexus\\gitnexus\\src\\core\\ingestion\\import-resolvers\\rust.ts", "source_location": "L53"}, {"caller_nid": "rust_resolverustimportinternal", "callee": "replace", "source_file": "E:\\_Knowledge\\ObsidianVault\\GitNexus\\gitnexus\\src\\core\\ingestion\\import-resolvers\\rust.ts", "source_location": "L54"}, {"caller_nid": "rust_tryrustmodulepath", "callee": "has", "source_file": "E:\\_Knowledge\\ObsidianVault\\GitNexus\\gitnexus\\src\\core\\ingestion\\import-resolvers\\rust.ts", "source_location": "L68"}, {"caller_nid": "rust_tryrustmodulepath", "callee": "has", "source_file": "E:\\_Knowledge\\ObsidianVault\\GitNexus\\gitnexus\\src\\core\\ingestion\\import-resolvers\\rust.ts", "source_location": "L70"}, {"caller_nid": "rust_tryrustmodulepath", "callee": "has", "source_file": "E:\\_Knowledge\\ObsidianVault\\GitNexus\\gitnexus\\src\\core\\ingestion\\import-resolvers\\rust.ts", "source_location": "L72"}, {"caller_nid": "rust_tryrustmodulepath", "callee": "lastIndexOf", "source_file": "E:\\_Knowledge\\ObsidianVault\\GitNexus\\gitnexus\\src\\core\\ingestion\\import-resolvers\\rust.ts", "source_location": "L76"}, {"caller_nid": "rust_tryrustmodulepath", "callee": "substring", "source_file": "E:\\_Knowledge\\ObsidianVault\\GitNexus\\gitnexus\\src\\core\\ingestion\\import-resolvers\\rust.ts", "source_location": "L78"}, {"caller_nid": "rust_tryrustmodulepath", "callee": "has", "source_file": "E:\\_Knowledge\\ObsidianVault\\GitNexus\\gitnexus\\src\\core\\ingestion\\import-resolvers\\rust.ts", "source_location": "L79"}, {"caller_nid": "rust_tryrustmodulepath", "callee": "has", "source_file": "E:\\_Knowledge\\ObsidianVault\\GitNexus\\gitnexus\\src\\core\\ingestion\\import-resolvers\\rust.ts", "source_location": "L80"}]}