{"nodes": [{"id": "switch", "label": "switch.tsx", "file_type": "code", "source_file": "tolaria/src/components/ui/switch.tsx", "source_location": "L1"}, {"id": "switch_switch", "label": "Switch()", "file_type": "code", "source_file": "tolaria/src/components/ui/switch.tsx", "source_location": "L10"}], "edges": [{"source": "switch", "target": "react", "relation": "imports_from", "confidence": "EXTRACTED", "source_file": "tolaria/src/components/ui/switch.tsx", "source_location": "L1", "weight": 1.0}, {"source": "switch", "target": "utils", "relation": "imports_from", "confidence": "EXTRACTED", "source_file": "tolaria/src/components/ui/switch.tsx", "source_location": "L3", "weight": 1.0}, {"source": "switch", "target": "switch_switch", "relation": "contains", "confidence": "EXTRACTED", "source_file": "tolaria/src/components/ui/switch.tsx", "source_location": "L10", "weight": 1.0}]}