{"nodes": [{"id": "useappnavigation_test", "label": "useAppNavigation.test.ts", "file_type": "code", "source_file": "tolaria/src/hooks/useAppNavigation.test.ts", "source_location": "L1"}, {"id": "useappnavigation_test_makeentry", "label": "makeEntry()", "file_type": "code", "source_file": "tolaria/src/hooks/useAppNavigation.test.ts", "source_location": "L6"}, {"id": "useappnavigation_test_rendernav", "label": "renderNav()", "file_type": "code", "source_file": "tolaria/src/hooks/useAppNavigation.test.ts", "source_location": "L17"}], "edges": [{"source": "useappnavigation_test", "target": "vitest", "relation": "imports_from", "confidence": "EXTRACTED", "source_file": "tolaria/src/hooks/useAppNavigation.test.ts", "source_location": "L1", "weight": 1.0}, {"source": "useappnavigation_test", "target": "react", "relation": "imports_from", "confidence": "EXTRACTED", "source_file": "tolaria/src/hooks/useAppNavigation.test.ts", "source_location": "L2", "weight": 1.0}, {"source": "useappnavigation_test", "target": "useappnavigation", "relation": "imports_from", "confidence": "EXTRACTED", "source_file": "tolaria/src/hooks/useAppNavigation.test.ts", "source_location": "L3", "weight": 1.0}, {"source": "useappnavigation_test", "target": "types", "relation": "imports_from", "confidence": "EXTRACTED", "source_file": "tolaria/src/hooks/useAppNavigation.test.ts", "source_location": "L4", "weight": 1.0}, {"source": "useappnavigation_test", "target": "useappnavigation_test_makeentry", "relation": "contains", "confidence": "EXTRACTED", "source_file": "tolaria/src/hooks/useAppNavigation.test.ts", "source_location": "L6", "weight": 1.0}, {"source": "useappnavigation_test", "target": "useappnavigation_test_rendernav", "relation": "contains", "confidence": "EXTRACTED", "source_file": "tolaria/src/hooks/useAppNavigation.test.ts", "source_location": "L17", "weight": 1.0}, {"source": "useappnavigation_test_rendernav", "target": "useappnavigation_test_makeentry", "relation": "calls", "confidence": "EXTRACTED", "source_file": "tolaria/src/hooks/useAppNavigation.test.ts", "source_location": "L21", "weight": 1.0}]}