{"nodes": [{"id": "home_sunny77_documents_obsidian_vault_ruflo_v2_bin_goal_js", "label": "goal.js", "file_type": "code", "source_file": "/home/sunny77/Documents/Obsidian Vault/ruflo/v2/bin/goal.js", "source_location": "L1"}, {"id": "goal_goalcommand", "label": "goalCommand()", "file_type": "code", "source_file": "/home/sunny77/Documents/Obsidian Vault/ruflo/v2/bin/goal.js", "source_location": "L10"}, {"id": "goal_initgoalmodule", "label": "initGoalModule()", "file_type": "code", "source_file": "/home/sunny77/Documents/Obsidian Vault/ruflo/v2/bin/goal.js", "source_location": "L32"}, {"id": "goal_exists", "label": "exists()", "file_type": "code", "source_file": "/home/sunny77/Documents/Obsidian Vault/ruflo/v2/bin/goal.js", "source_location": "L137"}], "edges": [{"source": "home_sunny77_documents_obsidian_vault_ruflo_v2_bin_goal_js", "target": "fs", "relation": "imports_from", "confidence": "EXTRACTED", "source_file": "/home/sunny77/Documents/Obsidian Vault/ruflo/v2/bin/goal.js", "source_location": "L6", "weight": 1.0}, {"source": "home_sunny77_documents_obsidian_vault_ruflo_v2_bin_goal_js", "target": "path", "relation": "imports_from", "confidence": "EXTRACTED", "source_file": "/home/sunny77/Documents/Obsidian Vault/ruflo/v2/bin/goal.js", "source_location": "L7", "weight": 1.0}, {"source": "home_sunny77_documents_obsidian_vault_ruflo_v2_bin_goal_js", "target": "chalk", "relation": "imports_from", "confidence": "EXTRACTED", "source_file": "/home/sunny77/Documents/Obsidian Vault/ruflo/v2/bin/goal.js", "source_location": "L8", "weight": 1.0}, {"source": "home_sunny77_documents_obsidian_vault_ruflo_v2_bin_goal_js", "target": "goal_goalcommand", "relation": "contains", "confidence": "EXTRACTED", "source_file": "/home/sunny77/Documents/Obsidian Vault/ruflo/v2/bin/goal.js", "source_location": "L10", "weight": 1.0}, {"source": "home_sunny77_documents_obsidian_vault_ruflo_v2_bin_goal_js", "target": "goal_initgoalmodule", "relation": "contains", "confidence": "EXTRACTED", "source_file": "/home/sunny77/Documents/Obsidian Vault/ruflo/v2/bin/goal.js", "source_location": "L32", "weight": 1.0}, {"source": "home_sunny77_documents_obsidian_vault_ruflo_v2_bin_goal_js", "target": "goal_exists", "relation": "contains", "confidence": "EXTRACTED", "source_file": "/home/sunny77/Documents/Obsidian Vault/ruflo/v2/bin/goal.js", "source_location": "L137", "weight": 1.0}, {"source": "goal_goalcommand", "target": "goal_initgoalmodule", "relation": "calls", "confidence": "EXTRACTED", "source_file": "/home/sunny77/Documents/Obsidian Vault/ruflo/v2/bin/goal.js", "source_location": "L25", "weight": 1.0}, {"source": "goal_initgoalmodule", "target": "goal_exists", "relation": "calls", "confidence": "EXTRACTED", "source_file": "/home/sunny77/Documents/Obsidian Vault/ruflo/v2/bin/goal.js", "source_location": "L40", "weight": 1.0}], "raw_calls": [{"caller_nid": "goal_goalcommand", "callee": "log", "source_file": "/home/sunny77/Documents/Obsidian Vault/ruflo/v2/bin/goal.js", "source_location": "L14"}, {"caller_nid": "goal_goalcommand", "callee": "magenta", "source_file": "/home/sunny77/Documents/Obsidian Vault/ruflo/v2/bin/goal.js", "source_location": "L14"}, {"caller_nid": "goal_goalcommand", "callee": "log", "source_file": "/home/sunny77/Documents/Obsidian Vault/ruflo/v2/bin/goal.js", "source_location": "L15"}, {"caller_nid": "goal_goalcommand", "callee": "log", "source_file": "/home/sunny77/Documents/Obsidian Vault/ruflo/v2/bin/goal.js", "source_location": "L16"}, {"caller_nid": "goal_goalcommand", "callee": "log", "source_file": "/home/sunny77/Documents/Obsidian Vault/ruflo/v2/bin/goal.js", "source_location": "L17"}, {"caller_nid": "goal_goalcommand", "callee": "log", "source_file": "/home/sunny77/Documents/Obsidian Vault/ruflo/v2/bin/goal.js", "source_location": "L18"}, {"caller_nid": "goal_goalcommand", "callee": "log", "source_file": "/home/sunny77/Documents/Obsidian Vault/ruflo/v2/bin/goal.js", "source_location": "L19"}, {"caller_nid": "goal_goalcommand", "callee": "log", "source_file": "/home/sunny77/Documents/Obsidian Vault/ruflo/v2/bin/goal.js", "source_location": "L20"}, {"caller_nid": "goal_goalcommand", "callee": "error", "source_file": "/home/sunny77/Documents/Obsidian Vault/ruflo/v2/bin/goal.js", "source_location": "L27"}, {"caller_nid": "goal_goalcommand", "callee": "red", "source_file": "/home/sunny77/Documents/Obsidian Vault/ruflo/v2/bin/goal.js", "source_location": "L27"}, {"caller_nid": "goal_goalcommand", "callee": "exit", "source_file": "/home/sunny77/Documents/Obsidian Vault/ruflo/v2/bin/goal.js", "source_location": "L28"}, {"caller_nid": "goal_initgoalmodule", "callee": "resolve", "source_file": "/home/sunny77/Documents/Obsidian Vault/ruflo/v2/bin/goal.js", "source_location": "L33"}, {"caller_nid": "goal_initgoalmodule", "callee": "cwd", "source_file": "/home/sunny77/Documents/Obsidian Vault/ruflo/v2/bin/goal.js", "source_location": "L33"}, {"caller_nid": "goal_initgoalmodule", "callee": "log", "source_file": "/home/sunny77/Documents/Obsidian Vault/ruflo/v2/bin/goal.js", "source_location": "L35"}, {"caller_nid": "goal_initgoalmodule", "callee": "magenta", "source_file": "/home/sunny77/Documents/Obsidian Vault/ruflo/v2/bin/goal.js", "source_location": "L35"}, {"caller_nid": "goal_initgoalmodule", "callee": "log", "source_file": "/home/sunny77/Documents/Obsidian Vault/ruflo/v2/bin/goal.js", "source_location": "L36"}, {"caller_nid": "goal_initgoalmodule", "callee": "gray", "source_file": "/home/sunny77/Documents/Obsidian Vault/ruflo/v2/bin/goal.js", "source_location": "L36"}, {"caller_nid": "goal_initgoalmodule", "callee": "log", "source_file": "/home/sunny77/Documents/Obsidian Vault/ruflo/v2/bin/goal.js", "source_location": "L41"}, {"caller_nid": "goal_initgoalmodule", "callee": "yellow", "source_file": "/home/sunny77/Documents/Obsidian Vault/ruflo/v2/bin/goal.js", "source_location": "L41"}, {"caller_nid": "goal_initgoalmodule", "callee": "mkdir", "source_file": "/home/sunny77/Documents/Obsidian Vault/ruflo/v2/bin/goal.js", "source_location": "L46"}, {"caller_nid": "goal_initgoalmodule", "callee": "writeFile", "source_file": "/home/sunny77/Documents/Obsidian Vault/ruflo/v2/bin/goal.js", "source_location": "L123"}, {"caller_nid": "goal_initgoalmodule", "callee": "join", "source_file": "/home/sunny77/Documents/Obsidian Vault/ruflo/v2/bin/goal.js", "source_location": "L123"}, {"caller_nid": "goal_initgoalmodule", "callee": "log", "source_file": "/home/sunny77/Documents/Obsidian Vault/ruflo/v2/bin/goal.js", "source_location": "L124"}, {"caller_nid": "goal_initgoalmodule", "callee": "gray", "source_file": "/home/sunny77/Documents/Obsidian Vault/ruflo/v2/bin/goal.js", "source_location": "L124"}, {"caller_nid": "goal_initgoalmodule", "callee": "log", "source_file": "/home/sunny77/Documents/Obsidian Vault/ruflo/v2/bin/goal.js", "source_location": "L126"}, {"caller_nid": "goal_initgoalmodule", "callee": "green", "source_file": "/home/sunny77/Documents/Obsidian Vault/ruflo/v2/bin/goal.js", "source_location": "L126"}, {"caller_nid": "goal_initgoalmodule", "callee": "log", "source_file": "/home/sunny77/Documents/Obsidian Vault/ruflo/v2/bin/goal.js", "source_location": "L127"}, {"caller_nid": "goal_initgoalmodule", "callee": "magenta", "source_file": "/home/sunny77/Documents/Obsidian Vault/ruflo/v2/bin/goal.js", "source_location": "L127"}, {"caller_nid": "goal_initgoalmodule", "callee": "log", "source_file": "/home/sunny77/Documents/Obsidian Vault/ruflo/v2/bin/goal.js", "source_location": "L128"}, {"caller_nid": "goal_initgoalmodule", "callee": "gray", "source_file": "/home/sunny77/Documents/Obsidian Vault/ruflo/v2/bin/goal.js", "source_location": "L128"}, {"caller_nid": "goal_initgoalmodule", "callee": "log", "source_file": "/home/sunny77/Documents/Obsidian Vault/ruflo/v2/bin/goal.js", "source_location": "L129"}, {"caller_nid": "goal_initgoalmodule", "callee": "gray", "source_file": "/home/sunny77/Documents/Obsidian Vault/ruflo/v2/bin/goal.js", "source_location": "L129"}, {"caller_nid": "goal_initgoalmodule", "callee": "error", "source_file": "/home/sunny77/Documents/Obsidian Vault/ruflo/v2/bin/goal.js", "source_location": "L132"}, {"caller_nid": "goal_initgoalmodule", "callee": "red", "source_file": "/home/sunny77/Documents/Obsidian Vault/ruflo/v2/bin/goal.js", "source_location": "L132"}, {"caller_nid": "goal_initgoalmodule", "callee": "exit", "source_file": "/home/sunny77/Documents/Obsidian Vault/ruflo/v2/bin/goal.js", "source_location": "L133"}, {"caller_nid": "goal_exists", "callee": "access", "source_file": "/home/sunny77/Documents/Obsidian Vault/ruflo/v2/bin/goal.js", "source_location": "L139"}]}