{"nodes": [{"id": "e_knowledge_obsidianvault_gitnexus_gitnexus_test_fixtures_group_test_frontend_src_api_users_ts", "label": "users.ts", "file_type": "code", "source_file": "E:\\_Knowledge\\ObsidianVault\\GitNexus\\gitnexus\\test\\fixtures\\group\\test-frontend\\src\\api\\users.ts", "source_location": "L1"}, {"id": "users_fetchusers", "label": "fetchUsers()", "file_type": "code", "source_file": "E:\\_Knowledge\\ObsidianVault\\GitNexus\\gitnexus\\test\\fixtures\\group\\test-frontend\\src\\api\\users.ts", "source_location": "L1"}, {"id": "users_createuser", "label": "createUser()", "file_type": "code", "source_file": "E:\\_Knowledge\\ObsidianVault\\GitNexus\\gitnexus\\test\\fixtures\\group\\test-frontend\\src\\api\\users.ts", "source_location": "L6"}, {"id": "users_fetchuser", "label": "fetchUser()", "file_type": "code", "source_file": "E:\\_Knowledge\\ObsidianVault\\GitNexus\\gitnexus\\test\\fixtures\\group\\test-frontend\\src\\api\\users.ts", "source_location": "L15"}], "edges": [{"source": "e_knowledge_obsidianvault_gitnexus_gitnexus_test_fixtures_group_test_frontend_src_api_users_ts", "target": "users_fetchusers", "relation": "contains", "confidence": "EXTRACTED", "source_file": "E:\\_Knowledge\\ObsidianVault\\GitNexus\\gitnexus\\test\\fixtures\\group\\test-frontend\\src\\api\\users.ts", "source_location": "L1", "weight": 1.0}, {"source": "e_knowledge_obsidianvault_gitnexus_gitnexus_test_fixtures_group_test_frontend_src_api_users_ts", "target": "users_createuser", "relation": "contains", "confidence": "EXTRACTED", "source_file": "E:\\_Knowledge\\ObsidianVault\\GitNexus\\gitnexus\\test\\fixtures\\group\\test-frontend\\src\\api\\users.ts", "source_location": "L6", "weight": 1.0}, {"source": "e_knowledge_obsidianvault_gitnexus_gitnexus_test_fixtures_group_test_frontend_src_api_users_ts", "target": "users_fetchuser", "relation": "contains", "confidence": "EXTRACTED", "source_file": "E:\\_Knowledge\\ObsidianVault\\GitNexus\\gitnexus\\test\\fixtures\\group\\test-frontend\\src\\api\\users.ts", "source_location": "L15", "weight": 1.0}], "raw_calls": [{"caller_nid": "users_fetchusers", "callee": "fetch", "source_file": "E:\\_Knowledge\\ObsidianVault\\GitNexus\\gitnexus\\test\\fixtures\\group\\test-frontend\\src\\api\\users.ts", "source_location": "L2"}, {"caller_nid": "users_fetchusers", "callee": "json", "source_file": "E:\\_Knowledge\\ObsidianVault\\GitNexus\\gitnexus\\test\\fixtures\\group\\test-frontend\\src\\api\\users.ts", "source_location": "L3"}, {"caller_nid": "users_createuser", "callee": "fetch", "source_file": "E:\\_Knowledge\\ObsidianVault\\GitNexus\\gitnexus\\test\\fixtures\\group\\test-frontend\\src\\api\\users.ts", "source_location": "L7"}, {"caller_nid": "users_createuser", "callee": "stringify", "source_file": "E:\\_Knowledge\\ObsidianVault\\GitNexus\\gitnexus\\test\\fixtures\\group\\test-frontend\\src\\api\\users.ts", "source_location": "L9"}, {"caller_nid": "users_createuser", "callee": "json", "source_file": "E:\\_Knowledge\\ObsidianVault\\GitNexus\\gitnexus\\test\\fixtures\\group\\test-frontend\\src\\api\\users.ts", "source_location": "L12"}, {"caller_nid": "users_fetchuser", "callee": "fetch", "source_file": "E:\\_Knowledge\\ObsidianVault\\GitNexus\\gitnexus\\test\\fixtures\\group\\test-frontend\\src\\api\\users.ts", "source_location": "L16"}, {"caller_nid": "users_fetchuser", "callee": "json", "source_file": "E:\\_Knowledge\\ObsidianVault\\GitNexus\\gitnexus\\test\\fixtures\\group\\test-frontend\\src\\api\\users.ts", "source_location": "L17"}]}