{"nodes": [{"id": "agent_loop", "label": "agent_loop.py", "file_type": "code", "source_file": "genericagent/agent_loop.py", "source_location": "L1"}, {"id": "agent_loop_stepoutcome", "label": "StepOutcome", "file_type": "code", "source_file": "genericagent/agent_loop.py", "source_location": "L5"}, {"id": "agent_loop_try_call_generator", "label": "try_call_generator()", "file_type": "code", "source_file": "genericagent/agent_loop.py", "source_location": "L9"}, {"id": "agent_loop_basehandler", "label": "BaseHandler", "file_type": "code", "source_file": "genericagent/agent_loop.py", "source_location": "L14"}, {"id": "agent_loop_basehandler_tool_before_callback", "label": ".tool_before_callback()", "file_type": "code", "source_file": "genericagent/agent_loop.py", "source_location": "L15"}, {"id": "agent_loop_basehandler_tool_after_callback", "label": ".tool_after_callback()", "file_type": "code", "source_file": "genericagent/agent_loop.py", "source_location": "L16"}, {"id": "agent_loop_basehandler_turn_end_callback", "label": ".turn_end_callback()", "file_type": "code", "source_file": "genericagent/agent_loop.py", "source_location": "L17"}, {"id": "agent_loop_basehandler_dispatch", "label": ".dispatch()", "file_type": "code", "source_file": "genericagent/agent_loop.py", "source_location": "L18"}, {"id": "agent_loop_json_default", "label": "json_default()", "file_type": "code", "source_file": "genericagent/agent_loop.py", "source_location": "L31"}, {"id": "agent_loop_exhaust", "label": "exhaust()", "file_type": "code", "source_file": "genericagent/agent_loop.py", "source_location": "L32"}, {"id": "agent_loop_get_pretty_json", "label": "get_pretty_json()", "file_type": "code", "source_file": "genericagent/agent_loop.py", "source_location": "L37"}, {"id": "agent_loop_agent_runner_loop", "label": "agent_runner_loop()", "file_type": "code", "source_file": "genericagent/agent_loop.py", "source_location": "L42"}, {"id": "agent_loop_clean_content", "label": "_clean_content()", "file_type": "code", "source_file": "genericagent/agent_loop.py", "source_location": "L99"}, {"id": "agent_loop_compact_tool_args", "label": "_compact_tool_args()", "file_type": "code", "source_file": "genericagent/agent_loop.py", "source_location": "L113"}], "edges": [{"source": "agent_loop", "target": "json", "relation": "imports", "confidence": "EXTRACTED", "source_file": "genericagent/agent_loop.py", "source_location": "L1", "weight": 1.0}, {"source": "agent_loop", "target": "re", "relation": "imports", "confidence": "EXTRACTED", "source_file": "genericagent/agent_loop.py", "source_location": "L1", "weight": 1.0}, {"source": "agent_loop", "target": "os", "relation": "imports", "confidence": "EXTRACTED", "source_file": "genericagent/agent_loop.py", "source_location": "L1", "weight": 1.0}, {"source": "agent_loop", "target": "dataclasses", "relation": "imports_from", "confidence": "EXTRACTED", "source_file": "genericagent/agent_loop.py", "source_location": "L2", "weight": 1.0}, {"source": "agent_loop", "target": "typing", "relation": "imports_from", "confidence": "EXTRACTED", "source_file": "genericagent/agent_loop.py", "source_location": "L3", "weight": 1.0}, {"source": "agent_loop", "target": "agent_loop_stepoutcome", "relation": "contains", "confidence": "EXTRACTED", "source_file": "genericagent/agent_loop.py", "source_location": "L5", "weight": 1.0}, {"source": "agent_loop", "target": "agent_loop_try_call_generator", "relation": "contains", "confidence": "EXTRACTED", "source_file": "genericagent/agent_loop.py", "source_location": "L9", "weight": 1.0}, {"source": "agent_loop", "target": "agent_loop_basehandler", "relation": "contains", "confidence": "EXTRACTED", "source_file": "genericagent/agent_loop.py", "source_location": "L14", "weight": 1.0}, {"source": "agent_loop_basehandler", "target": "agent_loop_basehandler_tool_before_callback", "relation": "method", "confidence": "EXTRACTED", "source_file": "genericagent/agent_loop.py", "source_location": "L15", "weight": 1.0}, {"source": "agent_loop_basehandler", "target": "agent_loop_basehandler_tool_after_callback", "relation": "method", "confidence": "EXTRACTED", "source_file": "genericagent/agent_loop.py", "source_location": "L16", "weight": 1.0}, {"source": "agent_loop_basehandler", "target": "agent_loop_basehandler_turn_end_callback", "relation": "method", "confidence": "EXTRACTED", "source_file": "genericagent/agent_loop.py", "source_location": "L17", "weight": 1.0}, {"source": "agent_loop_basehandler", "target": "agent_loop_basehandler_dispatch", "relation": "method", "confidence": "EXTRACTED", "source_file": "genericagent/agent_loop.py", "source_location": "L18", "weight": 1.0}, {"source": "agent_loop", "target": "agent_loop_json_default", "relation": "contains", "confidence": "EXTRACTED", "source_file": "genericagent/agent_loop.py", "source_location": "L31", "weight": 1.0}, {"source": "agent_loop", "target": "agent_loop_exhaust", "relation": "contains", "confidence": "EXTRACTED", "source_file": "genericagent/agent_loop.py", "source_location": "L32", "weight": 1.0}, {"source": "agent_loop", "target": "agent_loop_get_pretty_json", "relation": "contains", "confidence": "EXTRACTED", "source_file": "genericagent/agent_loop.py", "source_location": "L37", "weight": 1.0}, {"source": "agent_loop", "target": "agent_loop_agent_runner_loop", "relation": "contains", "confidence": "EXTRACTED", "source_file": "genericagent/agent_loop.py", "source_location": "L42", "weight": 1.0}, {"source": "agent_loop", "target": "agent_loop_clean_content", "relation": "contains", "confidence": "EXTRACTED", "source_file": "genericagent/agent_loop.py", "source_location": "L99", "weight": 1.0}, {"source": "agent_loop", "target": "agent_loop_compact_tool_args", "relation": "contains", "confidence": "EXTRACTED", "source_file": "genericagent/agent_loop.py", "source_location": "L113", "weight": 1.0}, {"source": "agent_loop_basehandler_dispatch", "target": "agent_loop_try_call_generator", "relation": "calls", "confidence": "EXTRACTED", "source_file": "genericagent/agent_loop.py", "source_location": "L22", "weight": 1.0}, {"source": "agent_loop_basehandler_dispatch", "target": "agent_loop_stepoutcome", "relation": "calls", "confidence": "EXTRACTED", "source_file": "genericagent/agent_loop.py", "source_location": "L26", "weight": 1.0}, {"source": "agent_loop_agent_runner_loop", "target": "agent_loop_exhaust", "relation": "calls", "confidence": "EXTRACTED", "source_file": "genericagent/agent_loop.py", "source_location": "L57", "weight": 1.0}, {"source": "agent_loop_agent_runner_loop", "target": "agent_loop_clean_content", "relation": "calls", "confidence": "EXTRACTED", "source_file": "genericagent/agent_loop.py", "source_location": "L58", "weight": 1.0}, {"source": "agent_loop_agent_runner_loop", "target": "agent_loop_get_pretty_json", "relation": "calls", "confidence": "EXTRACTED", "source_file": "genericagent/agent_loop.py", "source_location": "L70", "weight": 1.0}, {"source": "agent_loop_agent_runner_loop", "target": "agent_loop_compact_tool_args", "relation": "calls", "confidence": "EXTRACTED", "source_file": "genericagent/agent_loop.py", "source_location": "L71", "weight": 1.0}, {"source": "agent_loop_agent_runner_loop", "target": "agent_loop_basehandler_dispatch", "relation": "calls", "confidence": "EXTRACTED", "source_file": "genericagent/agent_loop.py", "source_location": "L73", "weight": 1.0}, {"source": "agent_loop_agent_runner_loop", "target": "agent_loop_basehandler_turn_end_callback", "relation": "calls", "confidence": "EXTRACTED", "source_file": "genericagent/agent_loop.py", "source_location": "L94", "weight": 1.0}]}