{"nodes": [{"id": "e_knowledge_obsidianvault_infinitebrain_ruflo_ruflo_src_ruvocal_src_routes_conversation_id_page_ts", "label": "+page.ts", "file_type": "code", "source_file": "E:\\_Knowledge\\ObsidianVault\\InfiniteBrain\\ruflo\\ruflo\\src\\ruvocal\\src\\routes\\conversation\\[id]\\+page.ts", "source_location": "L1"}, {"id": "page_load", "label": "load()", "file_type": "code", "source_file": "E:\\_Knowledge\\ObsidianVault\\InfiniteBrain\\ruflo\\ruflo\\src\\ruvocal\\src\\routes\\conversation\\[id]\\+page.ts", "source_location": "L20"}], "edges": [{"source": "e_knowledge_obsidianvault_infinitebrain_ruflo_ruflo_src_ruvocal_src_routes_conversation_id_page_ts", "target": "apiclient", "relation": "imports_from", "confidence": "EXTRACTED", "source_file": "E:\\_Knowledge\\ObsidianVault\\InfiniteBrain\\ruflo\\ruflo\\src\\ruvocal\\src\\routes\\conversation\\[id]\\+page.ts", "source_location": "L1", "weight": 1.0}, {"source": "e_knowledge_obsidianvault_infinitebrain_ruflo_ruflo_src_ruvocal_src_routes_conversation_id_page_ts", "target": "urldependency", "relation": "imports_from", "confidence": "EXTRACTED", "source_file": "E:\\_Knowledge\\ObsidianVault\\InfiniteBrain\\ruflo\\ruflo\\src\\ruvocal\\src\\routes\\conversation\\[id]\\+page.ts", "source_location": "L2", "weight": 1.0}, {"source": "e_knowledge_obsidianvault_infinitebrain_ruflo_ruflo_src_ruvocal_src_routes_conversation_id_page_ts", "target": "kit", "relation": "imports_from", "confidence": "EXTRACTED", "source_file": "E:\\_Knowledge\\ObsidianVault\\InfiniteBrain\\ruflo\\ruflo\\src\\ruvocal\\src\\routes\\conversation\\[id]\\+page.ts", "source_location": "L3", "weight": 1.0}, {"source": "e_knowledge_obsidianvault_infinitebrain_ruflo_ruflo_src_ruvocal_src_routes_conversation_id_page_ts", "target": "paths", "relation": "imports_from", "confidence": "EXTRACTED", "source_file": "E:\\_Knowledge\\ObsidianVault\\InfiniteBrain\\ruflo\\ruflo\\src\\ruvocal\\src\\routes\\conversation\\[id]\\+page.ts", "source_location": "L4", "weight": 1.0}, {"source": "e_knowledge_obsidianvault_infinitebrain_ruflo_ruflo_src_ruvocal_src_routes_conversation_id_page_ts", "target": "e_knowledge_obsidianvault_infinitebrain_ruflo_ruflo_src_ruvocal_src_routes_conversation_id_types", "relation": "imports_from", "confidence": "EXTRACTED", "source_file": "E:\\_Knowledge\\ObsidianVault\\InfiniteBrain\\ruflo\\ruflo\\src\\ruvocal\\src\\routes\\conversation\\[id]\\+page.ts", "source_location": "L5", "weight": 1.0}, {"source": "e_knowledge_obsidianvault_infinitebrain_ruflo_ruflo_src_ruvocal_src_routes_conversation_id_page_ts", "target": "message", "relation": "imports_from", "confidence": "EXTRACTED", "source_file": "E:\\_Knowledge\\ObsidianVault\\InfiniteBrain\\ruflo\\ruflo\\src\\ruvocal\\src\\routes\\conversation\\[id]\\+page.ts", "source_location": "L6", "weight": 1.0}, {"source": "e_knowledge_obsidianvault_infinitebrain_ruflo_ruflo_src_ruvocal_src_routes_conversation_id_page_ts", "target": "page_load", "relation": "contains", "confidence": "EXTRACTED", "source_file": "E:\\_Knowledge\\ObsidianVault\\InfiniteBrain\\ruflo\\ruflo\\src\\ruvocal\\src\\routes\\conversation\\[id]\\+page.ts", "source_location": "L20", "weight": 1.0}], "raw_calls": [{"caller_nid": "page_load", "callee": "depends", "source_file": "E:\\_Knowledge\\ObsidianVault\\InfiniteBrain\\ruflo\\ruflo\\src\\ruvocal\\src\\routes\\conversation\\[id]\\+page.ts", "source_location": "L21"}, {"caller_nid": "page_load", "callee": "useAPIClient", "source_file": "E:\\_Knowledge\\ObsidianVault\\InfiniteBrain\\ruflo\\ruflo\\src\\ruvocal\\src\\routes\\conversation\\[id]\\+page.ts", "source_location": "L23"}, {"caller_nid": "page_load", "callee": "parent", "source_file": "E:\\_Knowledge\\ObsidianVault\\InfiniteBrain\\ruflo\\ruflo\\src\\ruvocal\\src\\routes\\conversation\\[id]\\+page.ts", "source_location": "L27"}, {"caller_nid": "page_load", "callee": "get", "source_file": "E:\\_Knowledge\\ObsidianVault\\InfiniteBrain\\ruflo\\ruflo\\src\\ruvocal\\src\\routes\\conversation\\[id]\\+page.ts", "source_location": "L30"}, {"caller_nid": "page_load", "callee": "then", "source_file": "E:\\_Knowledge\\ObsidianVault\\InfiniteBrain\\ruflo\\ruflo\\src\\ruvocal\\src\\routes\\conversation\\[id]\\+page.ts", "source_location": "L34"}, {"caller_nid": "page_load", "callee": "post", "source_file": "E:\\_Knowledge\\ObsidianVault\\InfiniteBrain\\ruflo\\ruflo\\src\\ruvocal\\src\\routes\\conversation\\[id]\\+page.ts", "source_location": "L34"}, {"caller_nid": "page_load", "callee": "redirect", "source_file": "E:\\_Knowledge\\ObsidianVault\\InfiniteBrain\\ruflo\\ruflo\\src\\ruvocal\\src\\routes\\conversation\\[id]\\+page.ts", "source_location": "L43"}, {"caller_nid": "page_load", "callee": "then", "source_file": "E:\\_Knowledge\\ObsidianVault\\InfiniteBrain\\ruflo\\ruflo\\src\\ruvocal\\src\\routes\\conversation\\[id]\\+page.ts", "source_location": "L53"}, {"caller_nid": "page_load", "callee": "get", "source_file": "E:\\_Knowledge\\ObsidianVault\\InfiniteBrain\\ruflo\\ruflo\\src\\ruvocal\\src\\routes\\conversation\\[id]\\+page.ts", "source_location": "L53"}, {"caller_nid": "page_load", "callee": "conversations", "source_file": "E:\\_Knowledge\\ObsidianVault\\InfiniteBrain\\ruflo\\ruflo\\src\\ruvocal\\src\\routes\\conversation\\[id]\\+page.ts", "source_location": "L53"}, {"caller_nid": "page_load", "callee": "get", "source_file": "E:\\_Knowledge\\ObsidianVault\\InfiniteBrain\\ruflo\\ruflo\\src\\ruvocal\\src\\routes\\conversation\\[id]\\+page.ts", "source_location": "L55"}, {"caller_nid": "page_load", "callee": "redirect", "source_file": "E:\\_Knowledge\\ObsidianVault\\InfiniteBrain\\ruflo\\ruflo\\src\\ruvocal\\src\\routes\\conversation\\[id]\\+page.ts", "source_location": "L58"}]}